{
  "last_node_id": 14,
  "last_link_id": 18,
  "nodes": [
    {
      "id": 1,
      "type": "UNETLoader",
      "pos": [50, 100],
      "size": [315, 82],
      "flags": {},
      "order": 0,
      "mode": 0,
      "outputs": [
        {"name": "MODEL", "type": "MODEL", "links": [1, 2], "slot_index": 0}
      ],
      "properties": {"Node name for S&R": "UNETLoader"},
      "widgets_values": ["flux1-dev-fp8.safetensors", "fp8_e4m3fn"]
    },
    {
      "id": 2,
      "type": "DualCLIPLoader",
      "pos": [50, 220],
      "size": [315, 106],
      "flags": {},
      "order": 1,
      "mode": 0,
      "outputs": [
        {"name": "CLIP", "type": "CLIP", "links": [3], "slot_index": 0}
      ],
      "properties": {"Node name for S&R": "DualCLIPLoader"},
      "widgets_values": ["clip_l.safetensors", "t5xxl_fp8_e4m3fn.safetensors", "flux"]
    },
    {
      "id": 3,
      "type": "VAELoader",
      "pos": [50, 360],
      "size": [315, 58],
      "flags": {},
      "order": 2,
      "mode": 0,
      "outputs": [
        {"name": "VAE", "type": "VAE", "links": [4, 5], "slot_index": 0}
      ],
      "properties": {"Node name for S&R": "VAELoader"},
      "widgets_values": ["ae.safetensors"]
    },
    {
      "id": 4,
      "type": "LoadImage",
      "pos": [50, 450],
      "size": [315, 314],
      "flags": {},
      "order": 3,
      "mode": 0,
      "outputs": [
        {"name": "IMAGE", "type": "IMAGE", "links": [6], "slot_index": 0},
        {"name": "MASK", "type": "MASK", "links": null}
      ],
      "properties": {"Node name for S&R": "LoadImage"},
      "widgets_values": ["character_fullbody.png", "image"],
      "title": "Input Image"
    },
    {
      "id": 5,
      "type": "VAEEncode",
      "pos": [400, 450],
      "size": [210, 46],
      "flags": {},
      "order": 7,
      "mode": 0,
      "inputs": [
        {"name": "pixels", "type": "IMAGE", "link": 6},
        {"name": "vae", "type": "VAE", "link": 4}
      ],
      "outputs": [
        {"name": "LATENT", "type": "LATENT", "links": [7], "slot_index": 0}
      ],
      "properties": {"Node name for S&R": "VAEEncode"},
      "title": "Encode to Latent"
    },
    {
      "id": 6,
      "type": "CLIPTextEncode",
      "pos": [400, 100],
      "size": [400, 200],
      "flags": {},
      "order": 4,
      "mode": 0,
      "inputs": [
        {"name": "clip", "type": "CLIP", "link": 3}
      ],
      "outputs": [
        {"name": "CONDITIONING", "type": "CONDITIONING", "links": [8], "slot_index": 0}
      ],
      "properties": {"Node name for S&R": "CLIPTextEncode"},
      "widgets_values": ["full body character standing, vibrant stylized art style, bold blue and cyan colors, dramatic lighting, cel-shaded rendering, professional character design"],
      "title": "Positive Prompt"
    },
    {
      "id": 7,
      "type": "FluxGuidance",
      "pos": [850, 100],
      "size": [317, 58],
      "flags": {},
      "order": 8,
      "mode": 0,
      "inputs": [
        {"name": "conditioning", "type": "CONDITIONING", "link": 8}
      ],
      "outputs": [
        {"name": "CONDITIONING", "type": "CONDITIONING", "links": [9], "slot_index": 0}
      ],
      "properties": {"Node name for S&R": "FluxGuidance"},
      "widgets_values": [3.5]
    },
    {
      "id": 8,
      "type": "RandomNoise",
      "pos": [1200, 100],
      "size": [318, 95],
      "flags": {},
      "order": 5,
      "mode": 0,
      "outputs": [
        {"name": "NOISE", "type": "NOISE", "links": [10], "slot_index": 0}
      ],
      "properties": {"Node name for S&R": "RandomNoise"},
      "widgets_values": [999, "randomize"]
    },
    {
      "id": 9,
      "type": "KSamplerSelect",
      "pos": [1200, 230],
      "size": [239, 62],
      "flags": {},
      "order": 6,
      "mode": 0,
      "outputs": [
        {"name": "SAMPLER", "type": "SAMPLER", "links": [11], "slot_index": 0}
      ],
      "properties": {"Node name for S&R": "KSamplerSelect"},
      "widgets_values": ["euler"]
    },
    {
      "id": 10,
      "type": "SplitSigmasDenoise",
      "pos": [1200, 330],
      "size": [315, 82],
      "flags": {},
      "order": 9,
      "mode": 0,
      "inputs": [
        {"name": "model", "type": "MODEL", "link": 1}
      ],
      "outputs": [
        {"name": "SIGMAS", "type": "SIGMAS", "links": [12], "slot_index": 0}
      ],
      "properties": {"Node name for S&R": "SplitSigmasDenoise"},
      "widgets_values": [28, 0.6],
      "title": "Denoise Schedule (0.6 = 60%)"
    },
    {
      "id": 11,
      "type": "BasicGuider",
      "pos": [1200, 450],
      "size": [234, 101],
      "flags": {},
      "order": 10,
      "mode": 0,
      "inputs": [
        {"name": "model", "type": "MODEL", "link": 2},
        {"name": "conditioning", "type": "CONDITIONING", "link": 9}
      ],
      "outputs": [
        {"name": "GUIDER", "type": "GUIDER", "links": [13], "slot_index": 0}
      ],
      "properties": {"Node name for S&R": "BasicGuider"},
      "widgets_values": []
    },
    {
      "id": 12,
      "type": "SamplerCustomAdvanced",
      "pos": [1550, 100],
      "size": [237, 262],
      "flags": {},
      "order": 11,
      "mode": 0,
      "inputs": [
        {"name": "noise", "type": "NOISE", "link": 10},
        {"name": "guider", "type": "GUIDER", "link": 13},
        {"name": "sampler", "type": "SAMPLER", "link": 11},
        {"name": "sigmas", "type": "SIGMAS", "link": 12},
        {"name": "latent_image", "type": "LATENT", "link": 7}
      ],
      "outputs": [
        {"name": "output", "type": "LATENT", "links": [14], "slot_index": 0},
        {"name": "denoised_output", "type": "LATENT", "links": null}
      ],
      "properties": {"Node name for S&R": "SamplerCustomAdvanced"},
      "widgets_values": []
    },
    {
      "id": 13,
      "type": "VAEDecode",
      "pos": [1850, 100],
      "size": [237, 89],
      "flags": {},
      "order": 12,
      "mode": 0,
      "inputs": [
        {"name": "samples", "type": "LATENT", "link": 14},
        {"name": "vae", "type": "VAE", "link": 5}
      ],
      "outputs": [
        {"name": "IMAGE", "type": "IMAGE", "links": [15], "slot_index": 0}
      ],
      "properties": {"Node name for S&R": "VAEDecode"},
      "widgets_values": []
    },
    {
      "id": 14,
      "type": "SaveImage",
      "pos": [2150, 100],
      "size": [800, 900],
      "flags": {},
      "order": 13,
      "mode": 0,
      "inputs": [
        {"name": "images", "type": "IMAGE", "link": 15}
      ],
      "properties": {"Node name for S&R": "SaveImage"},
      "widgets_values": ["flux_img2img"]
    }
  ],
  "links": [
    [1, 1, 0, 10, 0, "MODEL"],
    [2, 1, 0, 11, 0, "MODEL"],
    [3, 2, 0, 6, 0, "CLIP"],
    [4, 3, 0, 5, 1, "VAE"],
    [5, 3, 0, 13, 1, "VAE"],
    [6, 4, 0, 5, 0, "IMAGE"],
    [7, 5, 0, 12, 4, "LATENT"],
    [8, 6, 0, 7, 0, "CONDITIONING"],
    [9, 7, 0, 11, 1, "CONDITIONING"],
    [10, 8, 0, 12, 0, "NOISE"],
    [11, 9, 0, 12, 2, "SAMPLER"],
    [12, 10, 0, 12, 3, "SIGMAS"],
    [13, 11, 0, 12, 1, "GUIDER"],
    [14, 12, 0, 13, 0, "LATENT"],
    [15, 13, 0, 14, 0, "IMAGE"]
  ],
  "groups": [],
  "config": {},
  "extra": {},
  "version": 0.4
}
